dhwani/__init__.py
dhwani/core/__init__.py
dhwani/core/converter.py
dhwani/core/core_utils/__init__.py
dhwani/core/core_utils/converter_utils.py
dhwani/mappings/__init__.py
dhwani/mappings/eng_hin.yaml
dhwani/mappings/eng_kan.yaml
dhwani/mappings/eng_tam.yaml
dhwani/mappings/supported_conversions.yaml
dhwani/mappings/utils.py
tests/__init__.py
tests/test_api.py
tests/test_mapping_integrity.py
dhwani-0.0.3.dist-info/LICENSE
dhwani-0.0.3.dist-info/METADATA
dhwani-0.0.3.dist-info/WHEEL
dhwani-0.0.3.dist-info/top_level.txt
dhwani-0.0.3.dist-info/RECORD
